anamator/__init__.py
anamator/basic_func.py
anamator/objects.py
animator/__init__.py
animator/basic_func.py
animator/objects.py
anamator-1.0.1.dist-info/LICENSE.txt
anamator-1.0.1.dist-info/METADATA
anamator-1.0.1.dist-info/WHEEL
anamator-1.0.1.dist-info/top_level.txt
anamator-1.0.1.dist-info/RECORD
